{
    "key": "group_6964cb12e59b9",
    "title": "Newsletetr",
    "fields": [
        {
            "key": "field_6964cc9ecb821",
            "label": "Newsletter",
            "name": "",
            "aria-label": "",
            "type": "accordion",
            "instructions": "",
            "required": 0,
            "conditional_logic": 0,
            "wrapper": {
                "width": "",
                "class": "",
                "id": ""
            },
            "open": 0,
            "multi_expand": 0,
            "endpoint": 0
        },
        {
            "key": "field_6964cc5d716f9",
            "label": "Newsletter",
            "name": "newsletter",
            "aria-label": "",
            "type": "group",
            "instructions": "",
            "required": 0,
            "conditional_logic": 0,
            "wrapper": {
                "width": "",
                "class": "",
                "id": ""
            },
            "layout": "block",
            "sub_fields": [
                {
                    "key": "field_6964cb1352dd3",
                    "label": "Title",
                    "name": "title",
                    "aria-label": "",
                    "type": "text",
                    "instructions": "",
                    "required": 0,
                    "conditional_logic": 0,
                    "wrapper": {
                        "width": "",
                        "class": "",
                        "id": ""
                    },
                    "default_value": "",
                    "maxlength": "",
                    "allow_in_bindings": 0,
                    "placeholder": "",
                    "prepend": "",
                    "append": ""
                },
                {
                    "key": "field_6964cb5452dd5",
                    "label": "Placeholder",
                    "name": "placeholder",
                    "aria-label": "",
                    "type": "text",
                    "instructions": "",
                    "required": 0,
                    "conditional_logic": 0,
                    "wrapper": {
                        "width": "",
                        "class": "",
                        "id": ""
                    },
                    "default_value": "",
                    "maxlength": "",
                    "allow_in_bindings": 0,
                    "placeholder": "",
                    "prepend": "",
                    "append": ""
                },
                {
                    "key": "field_6964cb2c52dd4",
                    "label": "Subtitle",
                    "name": "subtitle",
                    "aria-label": "",
                    "type": "textarea",
                    "instructions": "",
                    "required": 0,
                    "conditional_logic": 0,
                    "wrapper": {
                        "width": "",
                        "class": "",
                        "id": ""
                    },
                    "default_value": "",
                    "maxlength": "",
                    "allow_in_bindings": 0,
                    "rows": "",
                    "placeholder": "",
                    "new_lines": ""
                },
                {
                    "key": "field_6964cb6652dd6",
                    "label": "Button_text",
                    "name": "button_text",
                    "aria-label": "",
                    "type": "text",
                    "instructions": "",
                    "required": 0,
                    "conditional_logic": 0,
                    "wrapper": {
                        "width": "",
                        "class": "",
                        "id": ""
                    },
                    "default_value": "",
                    "maxlength": "",
                    "allow_in_bindings": 0,
                    "placeholder": "",
                    "prepend": "",
                    "append": ""
                }
            ]
        }
    ],
    "location": [
        [
            {
                "param": "page",
                "operator": "==",
                "value": "24"
            }
        ]
    ],
    "menu_order": 0,
    "position": "normal",
    "style": "default",
    "label_placement": "top",
    "instruction_placement": "label",
    "hide_on_screen": "",
    "active": true,
    "description": "",
    "show_in_rest": 0,
    "modified": 1768213675
}
